<?xml version="1.0" encoding="UTF-8"?>
<address>
  <street>Milchstrasse</street>
  <housenumber>23</housenumber>
  <postcode>26131</postcode>
  <city>Oldenburg</city>
  <country code="de">Germany</country>
  <mobilePhone operatorName='vodafone'>89473928231</mobilePhone>
  <homeOwner relation="none">Albert</homeOwner>
  <homeOwner onSite="false">Mayer</homeOwner>
  <state>Lower Saxony</state>
  <oldAddress>
    <street>Front St</street>
    <housenumber>1</housenumber>
    <postcode>A1A 1A1</postcode>
    <city>Toronto</city>
    <country code="ca">Canada</country>
  </oldAddress>
</address>